{
    "tid": "0004000000034800",
    "uid": "50010000006743",
    "name": "ドクターロートレックと\n忘却の騎士団",
    "formal_name": "ドクターロートレックと\n忘却の騎士団",
    "description": "この世の全ての謎を愛する考古学者ロートレック。彼の元に持ち込まれた、謎の地図をきっかけに始まる、壮大な冒険とミステリー。 \n<br>\n<br>本作品は、プレイヤーが主人公となり、パリを舞台に様々な謎を解いていく宝探しアドベンチャーです。\n<br>宝の地図を解読し、様々な場所を探索、クエストをこなして物語を進めていきます。宝の地図を片手に、洞窟を探検するドクター･ロートレック。相棒ソフィーと共に、謎のパリ地下洞窟を探検し、生きた財宝トレゾール･アビテを手に入れろ!\n<br>さらに、CVには、岸谷五朗さん、武井咲さん、バナナマンさんの豪華声優陣を起用し、物語を彩ります。",
    "release_date_on_eshop": null,
    "product_code": "CTR-P-ADLJ",
    "platform_name": "ニンテンドー3DSカードソフト",
    "region": "Japan",
    "genres": [
        "パズル",
        "アドベンチャー",
        "その他"
    ],
    "features": [
        "3D映像対応"
    ],
    "languages": [
        "日本語"
    ],
    "rating_system": {
        "name": "CERO",
        "age": "0"
    },
    "version": "v0.0.0",
    "disclaimer": null,
    "descriptors": []
}