{
    "tid": "0004000000199000",
    "uid": "50010000041897",
    "name": "튀어나와요 동물의 숲 amiibo+",
    "formal_name": "튀어나와요 동물의 숲 amiibo+",
    "description": "현실과 똑같은 시간이 흐르는 마을에서 유유자적 자유롭게 즐기는 생활!\n\n동물들이 사는 마을의 촌장이 되어, 마을을 가꾸며 사계절 특색 있는 이벤트나 동물들과의 교류를 즐길 수 있는『튀어나와요 동물의 숲』에 amiibo가 대응합니다.\n\n동물의 숲 시리즈의 amiibo나 amiibo 카드를 사용하면, 동물들이 마을에 놀러오거나 이사오는 경우도!\n\n게임을 할 수 있는 가구의 등장, 비밀 창고 증축, 터치 조작으로 가구 배치를 쉽게 할 수 있는 등 amiibo 대응 이외에도 추가된 즐길 거리가 다양합니다. ",
    "release_date_on_eshop": null,
    "product_code": "CTR-P-EAAK",
    "platform_name": "닌텐도 3DS 패키지",
    "region": "Korea",
    "genres": [
        "커뮤니케이션"
    ],
    "features": [
        "인터넷 대응",
        "3D 영상 대응",
        "로컬 플레이 대응",
        "엇갈림 통신 대응",
        "어느새 통신 대응",
        "Mii",
        "Nintendo Network",
        "amiibo"
    ],
    "languages": [
        "한국어"
    ],
    "rating_system": {
        "name": "GRB",
        "age": "0"
    },
    "version": "v5.0.0",
    "disclaimer": "본 소프트웨어를 사용하기 전에 HOME 메뉴의「안전을 위한 주의사항」을 선택하여 내용을 확인해 주십시오.\n여기에는 고객님의 건강와 안전을 위한 중요한 내용이 기재되어 있습니다. \n또한 본체의 사용설명서도 함께 읽어 주십시오. \n\n제명:튀어나와요 동물의 숲 amiibo+\n상호:한국닌텐도(주)\n이용등급:전체이용가\n등급분류번호:CC-NV-121123-014\n등급분류 일자:2012.11.23\n제작・배급업신고번호:게배 제2012-10호\n자막:한국어\n\n※『튀어나와요 동물의 숲』을 가지고 계신 분은 무료로 업데이트하여 곧바로 즐길 수 있습니다. 자세한 내용은 한국닌텐도 홈페이지에서 확인해 주세요. \n\n※ 소프트웨어 안에는 1개의 마을만 만들 수 있습니다. 마을 안에 4명까지 생활할 수 있으며, 각자의 집을 만들 수 있습니다.\n※ 처음 마을을 만든 플레이어만 촌장이 될 수 있습니다. 다른 플레이어는 주민이 됩니다.\n※ amiibo 카드는 일본어 버전으로 발매되며, 한글판 소프트웨어에서 사용할 수 있습니다.\n※ amiibo 카드의 캐릭터명은 게임 내에서 한글로 표시됩니다.",
    "descriptors": []
}