{
    "tid": "000480044B595256",
    "uid": "50010000007911",
    "name": "Rytmik Retrobits",
    "formal_name": "Rytmik Retrobits",
    "description": "Rytmik Retrobits is an application for\ncreating rhythmical and melodic\nthemes and for composing whole\nsongs. Its user interface blends the\nfast and well-arranged interface of\nclassic drum machines with the flexible\npattern interface of popular trackers\nand with a modern sound library. It\ncontains more than 180 carefully\nselected authentic retro sound\nsamples of electronic drums,\npercussion, bass, melodic instruments\nand effects from 8-bit and 16-bit\ncomputers and classic consoles.<br>\n<br>\nWith Rytmik Retrobits you can\nquickly and easily create the basic\nbuilding stone – an audio clip. It\nconsists of musical notations for up to\nfour instruments that you may\ntranspose, select their location in the\nstereo field, and modify their volume,\nreverse, shuffle (rhythm twist) and\npolyphony (with extended polyphony\nhandling), chorus/widening stereo\neffect, echo and arpeggiator. You may\narbitrarily combine up to 128 such\nclips in four tracks and create\ncomplex pieces of music. Moreover,\nyou have a collection of 10 pre-made\ncompositions at your disposal from\nwhich you may quickly compose your\nown pieces.<br>\n<br>\nRytmik Retrobits is not only for\nplaying with sounds; in the hands of a\nskillful musician it can become a\nserious musical instrument – a\nsurprisingly powerful pocket music\nstation. For the best musical\nexperience we recommend connecting\nheadphones or a quality speaker\nsystem. You’ll become the king of the\nretro party in no time...",
    "release_date_on_eshop": "2013-04-10",
    "product_code": "TWL-N-KYRV",
    "platform_name": "Nintendo DSiWare",
    "region": "Europe",
    "genres": [
        "Music"
    ],
    "features": [],
    "languages": [
        "English"
    ],
    "rating_system": {
        "name": null,
        "age": null
    },
    "version": "v0.3.0",
    "disclaimer": null,
    "descriptors": []
}