{
    "tid": "000480044B474C56",
    "uid": "50010000003622",
    "name": "Glow Artisan",
    "formal_name": "Glow Artisan",
    "description": "Solve mind-bending puzzles in this\nunique and colourful game!<br>\n<br>\nDescription:<br>\n<br>\nUse your wits and ingenuity to solve\nover 100 puzzles and earn over 300\nmedals. Play Time Trial, Randomizer,\nand Multiplayer modes for an endless\nsupply of new challenges! Create new\npuzzles with the built-in editor or use\nthe DSi Camera to turn your photos\ninto puzzles.<br>\n<br>\nPLAY<br>\n<br>\n- Over 100 pre-built levels!<br>\n<br>\n- Endless user-created and\nrandomly-generated puzzles!<br>\n<br>\n- Earn Trophies and Medals!<br>\n<br>\n- Unlock Time Trial and Randomizer\nmodes!<br>\n<br>\n- Get help from the Auto Solver\nwhen you are stuck!<br>\n<br>\nCREATE<br>\n<br>\n- Build your own puzzles from\nscratch with the Puzzle Creator!<br>\n<br>\n- Turn your world into Glow Puzzles\nby transforming DSi photos into\ncolourful challenges!<br>\n<br>\n- Use stored photos or take new\npictures from within the game!<br>\n<br>\nCONNECT<br>\n<br>\n- Challenge other players in Handoff,\na fun and competitive wireless battle\nof wits!<br>\n<br>\n- Wirelessly swap puzzles you've\ncreated with friends!",
    "release_date_on_eshop": "2013-04-10",
    "product_code": "TWL-N-KGLV",
    "platform_name": "Nintendo DSiWare",
    "region": "Europe",
    "genres": [
        "Puzzle",
        "Strategy"
    ],
    "features": [
        "Supports DS Wireless Play"
    ],
    "languages": [
        "English"
    ],
    "rating_system": {
        "name": "PEGI",
        "age": "3"
    },
    "version": "v0.0.0",
    "disclaimer": null,
    "descriptors": []
}