{
    "tid": "00040000001CDD00",
    "uid": "50010000044097",
    "name": "デジコロ じーさん邪 Vol.014\nくりだせ必殺技じゃっっ!!",
    "formal_name": "うごくまんが デジコロ でんぢゃらすじーさん邪\nVol.014 くりだせ必殺技じゃっっ!!",
    "description": "デジタルとコロコロコミックが合体！ それがデジコロです！\n<br>これまでにない新しいコミックがいよいよ登場します。\n<br>コロコロコミックでおなじみのあのキャラクターがデジコロになって、しゃべる！ 動き出す！\n<br>今までの電子コミックをはるかに超えたおもしろさを体感してください。\n<br>\n<br>圧倒的な技をくりだし対決するじーさんと校長。\n<br>じーさんのあらゆる必殺技が炸裂する中、\n<br>校長も必殺技が使えるようになる。\n<br>一進一退を繰り返す必殺技勝負。\n<br>最後にくりだしたじーさんの必殺技とは!?\n<br>\n<br>デジコロの情報はコロコロコミックをチェックしてください！\n<br>このあとも続々登場します！ 楽しみに待っていてください！",
    "release_date_on_eshop": "2018-01-10",
    "product_code": "CTR-N-J2ZJ",
    "platform_name": "ニンテンドー3DSダウンロードソフト",
    "region": "Japan",
    "genres": [
        "その他"
    ],
    "features": [],
    "languages": [
        "日本語"
    ],
    "rating_system": {
        "name": null,
        "age": null
    },
    "version": "v0.0.0",
    "disclaimer": "本ソフトは3D表示に対応しておりません。",
    "descriptors": []
}