{
    "tid": "000480044B4F424A",
    "uid": "50010000005482",
    "name": "顔トレミニ②\nステキな笑顔コース",
    "formal_name": "顔トレミニ②\nステキな笑顔コース",
    "description": "フェイスニングとは、顔の内側についている筋肉のトレーニング法です。顔に数多く存在する筋肉のひとつひとつを鍛えて、豊かな表情などをつくることを目的としています。\n本ソフト「ステキな笑顔コース」に収録されているフェイスニングは、「全顔」「小頬骨筋」「大頬骨筋」の3箇所のトレーニング。これらのフェイスニングを行うことで、目元や頬をスムーズにやわらかく動かして、ステキな笑顔を作れるようになることをめざします。\nDSiの画面上に映し出される自分の顔を見ながら、音声とアニメーションによるナビゲーションを参考に、効率的なフェイスニングを行うことができます。\n『顔トレミニ』シリーズには5つのコースがあり、それぞれ異なるフェイスニングが収録されています。5つのコースは連動しており、どのコースからでもフェイスニングの記録が参照できます。\n\n　①すっきり小顔コース\n　②ステキな笑顔コース（本ソフト）\n　③若々しい顔コース\n　④目と口の健康コース\n　⑤顔のリフレッシュコース\n\n※フェイスニングは、ニンテンドーDS用ソフト『大人のDS顔トレーニング』に収録されていたものと同じ内容です。（ニンテンドーDS用ソフト『大人のDS顔トレーニング』はDSi本体でご使用いただくことはできません）\n※フェイスニングの効果には個人差があります。\n",
    "release_date_on_eshop": "2009-09-09",
    "product_code": "TWL-N-KOBJ",
    "platform_name": "ニンテンドーDSiウェア",
    "region": "Japan",
    "genres": [
        "その他"
    ],
    "features": [],
    "languages": [
        "日本語"
    ],
    "rating_system": {
        "name": "CERO",
        "age": "0"
    },
    "version": "v0.0.0",
    "disclaimer": "本ソフトは、『今日からはじめるフェイスニング　顔トレミニ』シリーズ（全5コース）のうちのひとつ、「ステキな笑顔コース」です。\n「ステキな笑顔コース」には、「全顔」「小頬骨筋」「大頬骨筋」の3箇所のトレーニング（フェイスニング）が収録されています。\n\n※フェイスニングは、ニンテンドーDS用ソフト『大人のDS顔トレーニング』に収録されていたものと同じ内容です。（ニンテンドーDS用ソフト『大人のDS顔トレーニング』はDSi本体でご使用いただくことはできません）\n※フェイスニングの効果には個人差があります。\n\nニンテンドーDSiウェアは、3D表示に対応しておりません。\nソフトの紹介情報やソフト内の表現は、ニンテンドーDSi向けのものです。\nニンテンドー3DSでプレイする場合は、あてはまらない内容があったり、操作感が異なることがあります。あらかじめご了承ください。",
    "descriptors": []
}