{
    "tid": "000400000015EB00",
    "uid": "50010000029236",
    "name": "カラフリラックス 色彩合わせ",
    "formal_name": "カラフリラックス 色彩合わせ",
    "description": "『カラフリラックス 色彩合わせ』は、リラックスを目的とした、まったく新しいタイプ癒やし系パズルゲーム。\n<br>\n<br>制限時間やポイントを競うものではありません。ゲームで流れるリラックス度満点のサウンドトラックを楽しみながら、パズルを通じてアナタの疲れた心とカラダは癒されることでしょう。\n<br>\n<br>パズルの解き方はいたって簡単。同じ色のピースを合わせるだけです。急ぐ必要はありません。自分のペースでゆっくりと一つ一つのステージをクリアしていきましょう。リラックスとパズル解きに用意された460のステージが、アナタを幻想的な色彩の世界で包みます。\n<br>\n<br>仕事、学校、日常生活などでお疲れのアナタ、『カラフリラックス 色彩合わせ』で新しい安らぎとリラクゼーションを体験してみてください。",
    "release_date_on_eshop": "2015-01-07",
    "product_code": "CTR-N-JZNJ",
    "platform_name": "ニンテンドー3DSダウンロードソフト",
    "region": "Japan",
    "genres": [
        "パズル",
        "音楽"
    ],
    "features": [],
    "languages": [
        "日本語"
    ],
    "rating_system": {
        "name": "CERO",
        "age": "0"
    },
    "version": "v0.1.0",
    "disclaimer": "本ソフトは3D表示に対応しておりません。",
    "descriptors": []
}