{
    "tid": "0004000000154600",
    "uid": "50010000032455",
    "name": "BOXBOY!™",
    "formal_name": "BOXBOY!™",
    "description": "BOXBOY!™ is a 2D puzzle-platformer\navailable exclusively on\nNintendo 3DS™.\n<br/><br/>\nThe game features a minimalist style\nwith black-and-white graphics. The\ngameplay revolves around the main\ncharacter Qbby’s ability to create\nboxes he can use to protect himself,\nclimb on to, or activate switches.",
    "release_date_on_eshop": "2015-04-02",
    "product_code": "CTR-N-JCPP",
    "platform_name": "Nintendo 3DS (Download)",
    "region": "Europe",
    "genres": [
        "Platformer",
        "Puzzle"
    ],
    "features": [
        "Supports Download Play"
    ],
    "languages": [
        "English",
        "Spanish",
        "French",
        "German",
        "Italian"
    ],
    "rating_system": {
        "name": "PEGI",
        "age": "3"
    },
    "version": "v0.0.0",
    "disclaimer": null,
    "descriptors": []
}