{
    "tid": "000480044B534C56",
    "uid": "50010000006242",
    "name": "2-in-1 Solitaire",
    "formal_name": "2-in-1 Solitaire",
    "description": "2-in-1 Solitaire features two of the\nmost popular versions of the\nworld-famous card game – Spider and\nKlondike – with simple Touch Screen\ncontrols.<br>\n<br>\nIn Spider, the aim is to arrange cards\nin piles of a single suit from King\ndown to Ace, thereby removing the\npile from play. When all cards are\nremoved, you win the game.<br>\n<br>\nThe goal of Klondike is to arrange\ncards from Ace to King in piles, one\nfor each suit, on the four foundations.\nYou win when all cards have been\nmoved to the foundations.<br>\n<br>\nVarious difficulty levels are available\nfor Spider and Klondike, allowing\nbeginners or experts to enjoy the\ngame at their own pace.",
    "release_date_on_eshop": "2013-04-10",
    "product_code": "TWL-N-KSLV",
    "platform_name": "Nintendo DSiWare",
    "region": "Europe",
    "genres": [
        "Puzzle",
        "Board Game",
        "Other"
    ],
    "features": [],
    "languages": [],
    "rating_system": {
        "name": "PEGI",
        "age": "3"
    },
    "version": "v0.0.0",
    "disclaimer": null,
    "descriptors": []
}