{
    "tid": "0004000E001CA400",
    "uid": "50010000045597",
    "name": "更新データVer.1.2 バディファイト\n誕生！オレたちの最強バディ！",
    "formal_name": "更新データ Ver.1.2\nフューチャーカード バディファイト　誕生！オレたちの最強バディ！",
    "description": "ニンテンドー3DSソフト「フューチャーカード バディファイト　誕生！オレたちの最強バディ！」の更新データです。\nカード効果の不具合などを修正しました。\n「フューチャーカード バディファイト　誕生！オレたちの最強バディ！」をお持ちのお客様は、必ずダウンロードしてください。\n2018年7月18日以降は、更新データをダウンロードしたニンテンドー3DS本体でのみ、インターネット通信ファイトが可能です。\nまた、ローカル通信ファイトに関しては、更新データを適用したニンテンドー3DSと、適用していないニンテンドー3DSでの通信ファイトは行えなくなります。",
    "release_date_on_eshop": "2018-07-18",
    "product_code": "CTR-U-BFBJ",
    "platform_name": "更新データ",
    "region": "Japan",
    "genres": [
        "更新データ"
    ],
    "features": [],
    "languages": [
        "日本語"
    ],
    "rating_system": {
        "name": null,
        "age": null
    },
    "version": "v2.4.0",
    "disclaimer": "ニンテンドー3DSソフト『フューチャーカード バディファイト　誕生！オレたちの最強バディ！』の更新データです。本データはダウンロード後、ニンテンドー3DSのHOMEメニューにアイコンが表示されません。「本体設定」の「追加コンテンツ」に、本データが表示されますが、削除しないようにご注意ください。",
    "descriptors": []
}