{
    "tid": "000480044B584F56",
    "uid": "50010000012187",
    "name": "18th Gate",
    "formal_name": "18th Gate",
    "description": "In the realm of oblivion, an\nabandoned palace hides many\nvaluable treasures, but those who\nenter this place have no real hope of\never escaping.<br>\n<br>\nYou play as three different heroes.\nJourney through 18 different dungeon\nareas, facing various challenges,\nincluding random monsters, traps,\nlimited turns, hidden paths, etc.<br>\n<br>\nGame Features:<br>\n<br>\n-Adventure through a dungeon with\n18 different areas.<br>\n<br>\n-Random enemies, traps, and bonus\nitems.<br>\n<br>\n-Play with 3 heroes at the\nsame time, each with different abilities\nand skills.\n",
    "release_date_on_eshop": "2013-04-10",
    "product_code": "TWL-N-KXOV",
    "platform_name": "Nintendo DSiWare",
    "region": "Europe",
    "genres": [
        "Strategy",
        "Puzzle",
        "Adventure"
    ],
    "features": [],
    "languages": [
        "English"
    ],
    "rating_system": {
        "name": "PEGI",
        "age": "7"
    },
    "version": "v0.0.0",
    "disclaimer": null,
    "descriptors": []
}