{
    "tid": "00040000000FA300",
    "uid": "50010000015700",
    "name": "@SIMPLE DLシリーズ Vol.16\nTHE 密室からの脱出 ファミレス編",
    "formal_name": "@SIMPLE DLシリーズ Vol.16\nTHE 密室からの脱出\n～愉快なサルとファミレス編～",
    "description": "様々な場所に閉じ込められ、謎を解きながら脱出を試みるアドベンチャーゲーム。\n<br>今度の舞台はファミリーレストラン。友達と一緒に食事をしていたはずが、うっかり寝てしまって閉じ込められた主人公。あやしいサルのマスコットキャラクターが見つめる中、ファミレスでお馴染みのアイテムを使ってお店からの脱出を試みます。",
    "release_date_on_eshop": "2013-09-04",
    "product_code": "CTR-N-JF3J",
    "platform_name": "ニンテンドー3DSダウンロードソフト",
    "region": "Japan",
    "genres": [
        "アドベンチャー",
        "パズル"
    ],
    "features": [
        "3D映像対応"
    ],
    "languages": [
        "日本語"
    ],
    "rating_system": {
        "name": "CERO",
        "age": "0"
    },
    "version": "v0.0.0",
    "disclaimer": null,
    "descriptors": []
}