{
    "tid": "000480044B503245",
    "uid": "50010000003292",
    "name": "Petz® Dogz® Family",
    "formal_name": "Petz® Dogz® Family",
    "description": "There’s a whole family of dogs you can adopt and love! Take care of them, discover their unique personalities, and teach them fun tricks!\n\n• Choose from favorite breeds like Golden Retrievers and Labradors.\n• Give your dogs the best care: feed them, groom them, and discover their individual personalities—some will be funny, others will be shy!\n• Engage in fun activities with your pups, including playing with a flying disc and running obstacle courses, to turn them into talented dogs!",
    "release_date_on_eshop": "2010-08-02",
    "product_code": "TWL-N-KP2E",
    "platform_name": "Nintendo DSiWare",
    "region": "North America",
    "genres": [
        "Simulation",
        "Other"
    ],
    "features": [],
    "languages": [
        "English",
        "Spanish",
        "French"
    ],
    "rating_system": {
        "name": "ESRB",
        "age": "6"
    },
    "version": "v0.0.0",
    "disclaimer": null,
    "descriptors": []
}