{
    "tid": "000480044B44454A",
    "uid": "50010000005063",
    "name": "電卓＋TCG用ツール\nデュエル電卓カスタム",
    "formal_name": "電卓＋TCG用ツール\nデュエル電卓カスタム",
    "description": "すべてのトレーディングカードゲーム(TCG)で使える便利ソフトがついに発売。TCGがより楽しく遊べる機能をすべて盛り込んだツールが「デュエル電卓カスタム」です。 \nこの「デュエル電卓カスタム」を入れたDSi１台とゲームカードがあれば、 TCGをいつでもどこでも楽しめます。もうカード以外の備品をそろえたりするめんどうや、マーカーをなくしたりする心配もありません。\nこのソフトでは２人分のスコア計算とマーカー（6種類）、カード配置の記録ができます。\nダイス・コイン・時計・ストップウォッチ機能もついてます。\nまたよく遊ぶTCGのデータを「プリセット機能」であらかじめ設定しておくことで、どんなTCGでもすぐ遊べます。\nなお、ダイスは４，６，８，１０，１２，２０面体から選べ、最大10個まで振れるので、TCG以外にも、ボードゲームやTRPGを遊ぶ時にもご利用できます。",
    "release_date_on_eshop": "2009-09-30",
    "product_code": "TWL-N-KDEJ",
    "platform_name": "ニンテンドーDSiウェア",
    "region": "Japan",
    "genres": [
        "その他"
    ],
    "features": [],
    "languages": [
        "日本語"
    ],
    "rating_system": {
        "name": "CERO",
        "age": "0"
    },
    "version": "v0.0.0",
    "disclaimer": "ニンテンドーDSiウェアは、3D表示に対応しておりません。\nソフトの紹介情報やソフト内の表現は、ニンテンドーDSi向けのものです。\nニンテンドー3DSでプレイする場合は、あてはまらない内容があったり、操作感が異なることがあります。あらかじめご了承ください。",
    "descriptors": []
}