{
    "tid": "0004000000169C00",
    "uid": "50010000038397",
    "name": "ちゃおイラストクラブ",
    "formal_name": "ちゃおイラストクラブ",
    "description": "2020年12月23日(水)10時に、本ソフトの配信を終了いたしました。\n<br>\n<br>-------------------------------------------\n<br>かわいく! イラストがかわいく描けるオリジナルイラストと雑誌『ちゃお』(小学館)の人気6作品を収録!\n<br>上手に!! イラストが上手に描ける本格的なマジカルパレット!\n<br>みんなで!!! イラストがみんなで描ける! かんたんにお披露目&交換!\n<br>\n<br>★かわいく!\n<br>イラストクラブのオリジナルキャラクター サラ&モモとイラストマスターを目指そう!\n<br>動画や図を使ったレッスンでイラストが上手に描けるようになるよ!\n<br>オリジナルのお手本イラストや雑誌『ちゃお』(小学館)の人気6作品イラストを収録!\n<br>\n<br>★上手に!\n<br>･マジカルレッスン\n<br>目や髪の毛の描きかた、表情の違いや男の子と女の子の描き分けなどイラストを描くために必要なレッスンが盛りだくさん!\n<br>･マジカルパレット\n<br>りんかくを描くためのペン、えのぐ、えんぴつやさまざまなタッチで描けるペンなど、イラストを描くための道具を再現!\n<br>スクリーンやフキダシ、スタンプを使って描いたイラストをデコろう!\n<br>\n<br>★みんなで!\n<br>ローカル通信を使っておともだちとイラストの交換をしよう!\n<br>交換したおともだちのイラストに描き加えて通信、イラストリレーもできちゃう!\n<br>描いたイラストは簡単操作でSDカードに保存できて自由にお披露目!!",
    "release_date_on_eshop": "2015-11-26",
    "product_code": "CTR-N-BMDJ",
    "platform_name": "3DSカード/ダウンロードソフト",
    "region": "Japan",
    "genres": [
        "シミュレーション",
        "コミュニケーション"
    ],
    "features": [
        "ローカルプレイ対応",
        "いつの間に通信対応",
        "Nintendo Network"
    ],
    "languages": [
        "日本語"
    ],
    "rating_system": {
        "name": "CERO",
        "age": "0"
    },
    "version": "v0.1.0",
    "disclaimer": "本ソフトは3D表示に対応しておりません。\n<br>ソフトの内容はパッケージ版と同じです。\n<br>データ容量が大きいため、ソフトのダウンロードは長時間かかる場合があります。ニンテンドー3DS本体を充電しながらダウンロードしてください。",
    "descriptors": []
}