{
    "tid": "000400000006FF00",
    "uid": "50010000007241",
    "name": "ドンキーコングJR.",
    "formal_name": "ドンキーコングJR.",
    "description": "このソフトは、『ドンキーコング』の続編として1983年に発売されたファミリーコンピュータ用のアクションゲームです。マリオによってオリに閉じ込められた父・ドンキーコングを、息子・ジュニアが救出に向かいます。敵の攻撃をよけながらカギを集めて、ドンキーコングを助け出します。ジャングル風のステージでツルを上って下りて敵の攻撃をかわすのが特徴的。今となってはめずらしい、マリオが悪役として登場するゲームです。",
    "release_date_on_eshop": "2012-04-18",
    "product_code": "CTR-N-TAKJ",
    "platform_name": "ファミリーコンピュータ",
    "region": "Japan",
    "genres": [
        "アクション"
    ],
    "features": [],
    "languages": [
        "日本語"
    ],
    "rating_system": {
        "name": "CERO",
        "age": "0"
    },
    "version": "v1.0.0",
    "disclaimer": "このソフトは、原作のゲーム内容を、通信機能・拡張機能を除いてニンテンドー3DS上で再現したものです。原作とは、動作や表現等が異なる場合があります。あらかじめご了承ください。本ソフトは通信による2人同時プレイに対応していません。",
    "descriptors": []
}