{
    "tid": "0004000000126400",
    "uid": "50010000021146",
    "name": "ぐるぐるたまごっち!",
    "formal_name": "ぐるぐるたまごっち!",
    "description": "2018年9月28日(金)12時に、本ソフトの配信を終了いたしました。\n<br>\n<br>-------------------------------------------\n<br>■世界で遊ぼう!\n<br>こどもたちの行ってみたい場所ランキングから10のエリアを選出!\n<br>ロシアでフィギュアスケート、ハワイでフラ、ブラジルでサッカー、インドでカレー……\n<br>各国で、その国ならではのミニゲームが楽しめちゃうよ♪\n<br>\n<br>■世界でおしゃべりしよう!\n<br>登場キャラは100人以上!\n<br>シリーズ最大ボリュームのシナリオで、キャラクターとの深いコミュニケーションを楽しもう!\n<br>\n<br>■世界で学ぼう!\n<br>世界中のあいさつ、ご当地アイテム、首都、ランドマークなど、たくさんのことが学べちゃう!\n<br>出会った情報はスクラップブックでいつでも見ることができるよ♪\n<br>\n<br>■マイキャラをカスタマイズ!\n<br>マイキャラの顔や衣装を自由にカスタマイズすることができるよ!\n<br>いろんな国の民族衣装を集めておしゃれしちゃおう♪\n<br>\n<br>■マイルームもカスタマイズ!\n<br>世界中のインテリアを集めて、素敵なお部屋を作っちゃおう♪\n<br>\n<br>■充実の引き継ぎ機能!\n<br>前作『たまごっち!せーしゅんのドリームスクール』をプレイしたニンテンドー3DSで本作を遊ぶと、ドリームスクール特製衣装が解放されるよ!\n<br>マイキャラやマイルームは次回作へ引き継ぎもできるよ!",
    "release_date_on_eshop": "2014-04-24",
    "product_code": "CTR-N-BGGJ",
    "platform_name": "3DSカード/ダウンロードソフト",
    "region": "Japan",
    "genres": [
        "アドベンチャー",
        "学習",
        "コミュニケーション"
    ],
    "features": [
        "3D映像対応"
    ],
    "languages": [
        "日本語"
    ],
    "rating_system": {
        "name": "CERO",
        "age": "0"
    },
    "version": "v0.1.0",
    "disclaimer": "ソフトの内容はパッケージ版と同じです。\n<br>データ容量が大きいため、ソフトのダウンロードは長時間かかる場合があります。ニンテンドー3DS本体を充電しながらダウンロードしてください。",
    "descriptors": []
}