{
    "tid": "00040000000D0D00",
    "uid": "50010000013374",
    "name": "怪獣が出る金曜日",
    "formal_name": "怪獣が出る金曜日",
    "description": "主人公とその家族が暮らすのは、毎週金曜日に巨大怪獣が出現する東京郊外の町。人々は普通に生活して、駅には数分おきに新宿行きの私鉄電車がやってくる。\n<br>\n<br>「怪獣は本当のことなのに、なぜ脚本家がいるんだろ……」\n<br>主人公の小さな疑問から物語は大きくうねり始めます。\n<br>カード収集、美少女、昭和、自警団ヒーロー、そしてサイレント映画時代の子供の忍術遊びまで、幅広いモチーフを取り込んだ本作は、懐かしいほのぼのタッチのゲーム制作に定評があるクリエイター･綾部和(ミレニアムキッチン)による完全新作!\n<br>\n<br>アコースティックな手触りにこだわった坂本英城(ノイジークローク)の音楽や、主題歌『ボクは子ども』にもご注目ください。",
    "release_date_on_eshop": "2013-03-13",
    "product_code": "CTR-N-JKEJ",
    "platform_name": "ニンテンドー3DSダウンロードソフト",
    "region": "Japan",
    "genres": [
        "アドベンチャー"
    ],
    "features": [
        "3D映像対応"
    ],
    "languages": [
        "日本語"
    ],
    "rating_system": {
        "name": "CERO",
        "age": "0"
    },
    "version": "v0.0.0",
    "disclaimer": null,
    "descriptors": []
}