{
    "tid": "0004000000187A00",
    "uid": "50010000040925",
    "name": "3D ぷよぷよ通",
    "formal_name": "3D ぷよぷよ通",
    "description": "人気アクションパズル「ぷよぷよ」シリーズ第2作が3D化されて登場！ オリジナル版を忠実に再現した「アーケード」のほか、全登場キャラと対戦していく「かちぬき」モードを新たに追加。ローカルプレイ対応の対戦も可能です。（それぞれのニンテンドー3DS本体に本作か『セガ3D復刻アーカイブス2』が必要です）",
    "release_date_on_eshop": "2016-08-03",
    "product_code": "CTR-N-KY3J",
    "platform_name": "ニンテンドー3DSダウンロードソフト",
    "region": "Japan",
    "genres": [
        "パズル"
    ],
    "features": [
        "3D映像対応",
        "ローカルプレイ対応"
    ],
    "languages": [
        "日本語"
    ],
    "rating_system": {
        "name": "CERO",
        "age": "0"
    },
    "version": "v0.0.0",
    "disclaimer": null,
    "descriptors": []
}