{
    "tid": "000400000006DF00",
    "uid": "50010000007661",
    "name": "怪盗スティナと30の宝石",
    "formal_name": "怪盗スティナと30の宝石",
    "description": "「怪盗編」は、大怪盗スティナとなり刑事と大勢の警備ロボが守る中つぎつぎに怪盗ロボを放ち、大混雑の大乱闘の中目的の宝石を盗み出すという痛快なアクションゲームです。いつ見つかるか、いつ捕まるかのハラハラ･ドキドキ感、見事宝石を盗み出したときの爽快感がたまらないアクション RTS(リアルタイムストラテジー)です。\n<br>全ステージの宝石を盗み出したら、宝石を守る側の「刑事編」がプレイできるようになります。刑事を惑わすダミーの怪盗ロボと本物の怪盗を見極め、追い詰め捕まえます。洞察力と判断力が問われる頭脳プレイが要求されるゲームになります。\n<br>同じステージ上で立場が変わることによる、アクション性と頭脳が要求されるゲームを、あなたはクリアできるでしょうか!?",
    "release_date_on_eshop": "2011-10-19",
    "product_code": "CTR-N-JS3J",
    "platform_name": "ニンテンドー3DSダウンロードソフト",
    "region": "Japan",
    "genres": [
        "アクション",
        "シミュレーション"
    ],
    "features": [
        "3D映像対応"
    ],
    "languages": [
        "日本語"
    ],
    "rating_system": {
        "name": "CERO",
        "age": "12"
    },
    "version": "v0.1.0",
    "disclaimer": null,
    "descriptors": []
}