{
    "tid": "000480044B44584A",
    "uid": "50010000005083",
    "name": "X-RETURNS",
    "formal_name": "X-RETURNS",
    "description": "宇宙戦闘タンクVIXIV（ビクシブ）を操り、\n銀河の平和を取り戻せ！\n\n『X-RETURNS (エックス リターンズ)』は、\n20以上の惑星を巡り、それぞれの惑星で展開されるストーリーに沿って任務を遂行していく、シューティングアドベンチャーゲームです。\n\n自動スクロールで画面の奥へと進行するトンネルモードと、一定のエリア内で敵を倒したり情報やアイテムの探索をおこなうオールレンジモードの、2つのモードを交互に繰り返しながらゲームを進めます。\n\n1992年にゲームボーイで発売された前作\n『X (エックス)』の登場キャラクターや世界観を引き継ぎ、シンプルながらも印象的なビジュアルと、惑星に散りばめられた情報が、あなたの想像力を刺激します。\n",
    "release_date_on_eshop": "2010-06-30",
    "product_code": "TWL-N-KDXJ",
    "platform_name": "ニンテンドーDSiウェア",
    "region": "Japan",
    "genres": [
        "シューティング",
        "アドベンチャー"
    ],
    "features": [],
    "languages": [
        "日本語"
    ],
    "rating_system": {
        "name": "CERO",
        "age": "0"
    },
    "version": "v0.0.0",
    "disclaimer": "ニンテンドーDSiウェアは、3D表示に対応しておりません。\nソフトの紹介情報やソフト内の表現は、ニンテンドーDSi向けのものです。\nニンテンドー3DSでプレイする場合は、あてはまらない内容があったり、操作感が異なることがあります。あらかじめご了承ください。",
    "descriptors": []
}