{
    "tid": "000480044B43554A",
    "uid": "50010000005042",
    "name": "うそ発見器\n心の中をのぞいちゃお☆",
    "formal_name": "うそ発見器\n心の中をのぞいちゃお☆",
    "description": "質問に対する声の調子を検知して、心の動揺度を量って楽しむゲームです。 ゲーム内に登録されている質問の他に、自分で質問を作って登録したり、２人プレイ時には直接相手に質問して動揺度を量ることもできます。",
    "release_date_on_eshop": "2010-02-10",
    "product_code": "TWL-N-KCUJ",
    "platform_name": "ニンテンドーDSiウェア",
    "region": "Japan",
    "genres": [
        "シミュレーション",
        "テーブル",
        "その他"
    ],
    "features": [],
    "languages": [
        "日本語"
    ],
    "rating_system": {
        "name": "CERO",
        "age": "0"
    },
    "version": "v0.0.0",
    "disclaimer": "ニンテンドーDSiウェアは、3D表示に対応しておりません。\nソフトの紹介情報やソフト内の表現は、ニンテンドーDSi向けのものです。\nニンテンドー3DSでプレイする場合は、あてはまらない内容があったり、操作感が異なることがあります。あらかじめご了承ください。",
    "descriptors": []
}